[
  {
    "id": 1,
    "usuarioId": 101,
    "idEquipo": "21980107133GJ7000257"
  },
  {
    "id": 2,
    "usuarioId": 101,
    "idEquipo": "21980105812SJ4600371"
  },
  {
    "id": 3,
    "usuarioId": 101,
    "idEquipo": "21980105812SJ4600293"
  },
  {
    "id": 4,
    "usuarioId": 101,
    "idEquipo": "21980105812SJ4600373"
  },
  {
    "id": 5,
    "usuarioId": 101,
    "idEquipo": "21980105812SJ4600325"
  },
  {
    "id": 6,
    "usuarioId": 101,
    "idEquipo": "21980105812SJ4600326"
  },
  {
    "id": 7,
    "usuarioId": 101,
    "idEquipo": "21980105812SJ4600318"
  },
  {
    "id": 8,
    "usuarioId": 102,
    "idEquipo": "21980105812SJ4600297"
  },
  {
    "id": 9,
    "usuarioId": 102,
    "idEquipo": "21980105812SJ4600315"
  },
  {
    "id": 10,
    "usuarioId": 102,
    "idEquipo": "21980107133GJ7000255"
  },
  {
    "id": 11,
    "usuarioId": 102,
    "idEquipo": "21980105812SJ4600336"
  },
  {
    "id": 12,
    "usuarioId": 102,
    "idEquipo": "21980105812SJ4600332"
  },
  {
    "id": 13,
    "usuarioId": 102,
    "idEquipo": "21980105812SJ4600322"
  },
  {
    "id": 14,
    "usuarioId": 102,
    "idEquipo": "21980105812SJ4600338"
  },
  {
    "id": 15,
    "usuarioId": 102,
    "idEquipo": "21980105812SJ4600317"
  }
]
